optialgo/__init__.py
optialgo/__parent.py
optialgo/__utils.py
optialgo/classification.py
optialgo/dataset.py
optialgo/regression.py
optialgo/textDataset.py
optialgo/text_preprocessing.py
tests/__init__.py
tests/compress_file.py
tests/preprocessing_text.py
tests/test_dataset.py
tests/test_dataset_tab.py
tests/test_regression.py
tests/test_utils.py
tests/tokenizer_test.py
optialgo-1.0.3.dist-info/LICENSE
optialgo-1.0.3.dist-info/METADATA
optialgo-1.0.3.dist-info/WHEEL
optialgo-1.0.3.dist-info/top_level.txt
optialgo-1.0.3.dist-info/RECORD
