Metadata-Version: 2.1
Name: optialgo
Version: 1.0.3
Summary: OptiAlgo menyediakan solusi cepat dan andal untuk mencari algoritma terbaik bagi pengguna, serta memberikan fleksibilitas dalam menangani berbagai masalah data.
Home-page: https://github.com/nsandarma/OptiAlgo
Author: nsandarma
Author-email: nsandarma@gmail.com
License: MIT
Classifier: Programming Language :: Python :: 3
Classifier: License :: OSI Approved :: MIT License
Classifier: Operating System :: OS Independent
Requires-Python: >=3.10
License-File: LICENSE
Requires-Dist: scikit-learn
Requires-Dist: skfeature-chappers
Requires-Dist: xgboost
Requires-Dist: imblearn
Requires-Dist: category-encoders
Requires-Dist: matplotlib
Requires-Dist: seaborn
Requires-Dist: pandas
Requires-Dist: numpy ==1.26.4
Requires-Dist: rich
Requires-Dist: tqdm
Requires-Dist: nltk
Requires-Dist: sastrawi
Requires-Dist: nlp-id ==0.1.16.0
Requires-Dist: ipywidgets
